fsdiff/__init__.py
fsdiff/main.py
fsdiff-0.3.1.data/scripts/fsdiff
fsdiff-0.3.1.dist-info/DESCRIPTION.rst
fsdiff-0.3.1.dist-info/METADATA
fsdiff-0.3.1.dist-info/RECORD
fsdiff-0.3.1.dist-info/WHEEL
fsdiff-0.3.1.dist-info/metadata.json
fsdiff-0.3.1.dist-info/top_level.txt
