Metadata-Version: 2.0
Name: fsdiff
Version: 0.3.1
Summary: Byte to byte comparison of local disk images or filesystems
Home-page: https://github.com/wizofe/fsdiff
Author: Ioannis Valasakis
Author-email: code@wizofe.uk
License: GNU GPL v2
Platform: POSIX
Requires-Python: >=3.0
Requires-Dist: colorama
